vunnel/__init__.py
vunnel/__main__.py
vunnel/distribution.py
vunnel/provider.py
vunnel/result.py
vunnel/schema.py
vunnel/workspace.py
vunnel/cli/__init__.py
vunnel/cli/cli.py
vunnel/cli/config.py
vunnel/providers/__init__.py
vunnel/providers/alma/__init__.py
vunnel/providers/alma/git.py
vunnel/providers/alma/parser.py
vunnel/providers/alpine/__init__.py
vunnel/providers/alpine/parser.py
vunnel/providers/alpine/rejections.py
vunnel/providers/amazon/__init__.py
vunnel/providers/amazon/parser.py
vunnel/providers/arch/__init__.py
vunnel/providers/arch/parser.py
vunnel/providers/bitnami/__init__.py
vunnel/providers/bitnami/git.py
vunnel/providers/bitnami/parser.py
vunnel/providers/chainguard/__init__.py
vunnel/providers/chainguard_libraries/__init__.py
vunnel/providers/chainguard_libraries/openvex_parser.py
vunnel/providers/debian/__init__.py
vunnel/providers/debian/parser.py
vunnel/providers/echo/__init__.py
vunnel/providers/echo/parser.py
vunnel/providers/eol/DEVELOPING.md
vunnel/providers/eol/__init__.py
vunnel/providers/eol/generate_schema.py
vunnel/providers/eol/manager.py
vunnel/providers/epss/__init__.py
vunnel/providers/epss/manager.py
vunnel/providers/github/__init__.py
vunnel/providers/github/parser.py
vunnel/providers/kev/__init__.py
vunnel/providers/kev/manager.py
vunnel/providers/mariner/DEVELOPING.md
vunnel/providers/mariner/__init__.py
vunnel/providers/mariner/generate_models.py
vunnel/providers/mariner/parser.py
vunnel/providers/mariner/model/__init__.py
vunnel/providers/mariner/model/generated.py
vunnel/providers/minimos/__init__.py
vunnel/providers/minimos/parser.py
vunnel/providers/nvd/__init__.py
vunnel/providers/nvd/api.py
vunnel/providers/nvd/manager.py
vunnel/providers/nvd/overrides.py
vunnel/providers/oracle/__init__.py
vunnel/providers/oracle/parser.py
vunnel/providers/rhel/__init__.py
vunnel/providers/rhel/csaf_client.py
vunnel/providers/rhel/csaf_parser.py
vunnel/providers/rhel/oval_parser.py
vunnel/providers/rhel/parser.py
vunnel-0.50.0.dist-info/METADATA
vunnel-0.50.0.dist-info/WHEEL
vunnel-0.50.0.dist-info/entry_points.txt
vunnel-0.50.0.dist-info/licenses/LICENSE
vunnel-0.50.0.dist-info/RECORD
