Metadata-Version: 2.4
Name: vunnel
Version: 0.50.0
Summary: vunnel ~= 'vulnerability data funnel'
Project-URL: repository, https://github.com/anchore/vunnel
Author-email: Alex Goodman <alex.goodman@anchore.com>
License: Apache-2.0
License-File: LICENSE
Keywords: aggregator,data,grype,vulnerability,vulnerability-data
Classifier: Development Status :: 5 - Production/Stable
Classifier: Intended Audience :: Developers
Classifier: Intended Audience :: Information Technology
Classifier: Intended Audience :: System Administrators
Classifier: Natural Language :: English
Classifier: Operating System :: MacOS
Classifier: Operating System :: POSIX :: Linux
Classifier: Topic :: Security
Classifier: Topic :: Software Development :: Libraries :: Python Modules
Classifier: Topic :: Utilities
Requires-Python: <3.14,>=3.13
Requires-Dist: click<9.0.0,>=8.1.3
Requires-Dist: colorlog<7.0.0,>=6.7.0
Requires-Dist: cvss<4.0,>=2.6
Requires-Dist: defusedxml<1.0.0,>=0.7.1
Requires-Dist: ijson<4.0,>=2.5.1
Requires-Dist: importlib-metadata<9.0.0,>=7.0.1
Requires-Dist: iso8601<3.0.0,>=2.1.0
Requires-Dist: mashumaro<4.0,>=3.10
Requires-Dist: mergedeep<2.0.0,>=1.3.4
Requires-Dist: oras<1.0.0,>=0.1.0
Requires-Dist: orjson<4.0.0,>=3.8.6
Requires-Dist: packageurl-python<1.0.0,>=0.16.0
Requires-Dist: pytest-snapshot<1.0.0,>=0.9.0
Requires-Dist: python-dateutil<3.0.0,>=2.8.2
Requires-Dist: pyyaml<7.0,>=6.0
Requires-Dist: requests<3.0.0,>=2.28.1
Requires-Dist: sqlalchemy>=2.0.43
Requires-Dist: xsdata[cli,lxml,soap]<23.0,>=22.12
Requires-Dist: xxhash<4.0.0,>=3.1.0
Requires-Dist: zstandard<0.26,>=0.22
